rel/__init__.py
rel/mod_rel.py
ns_rep_imports-0.1.3.dist-info/LICENSE
ns_rep_imports-0.1.3.dist-info/METADATA
ns_rep_imports-0.1.3.dist-info/WHEEL
ns_rep_imports-0.1.3.dist-info/top_level.txt
ns_rep_imports-0.1.3.dist-info/RECORD
