Metadata-Version: 2.1
Name: ns-rep-imports
Version: 0.1.3
Summary: Namespace Realitive Import Generator
Home-page: https://github.com/Amourspirit/python-ns-rel-imports
Author: :Barry-Thomas-Paul: Moss
Author-email: bigbytetech@gmail.com
License: MIT
Keywords: import,namespace,rel,camel-to-snake
Platform: UNKNOWN
Classifier: License :: OSI Approved :: MIT License
Classifier: Programming Language :: Python :: 3
Classifier: Programming Language :: Python :: 3.6
Classifier: Programming Language :: Python :: 3.7
Classifier: Programming Language :: Python :: 3.8
Classifier: Programming Language :: Python :: 3.9
Classifier: Programming Language :: Python :: 3.10
Requires-Python: >=3.6.0
License-File: LICENSE
Requires-Dist: kwargshelper (>=2.7.1)
